spacy_api/__init__.py
spacy_api/__init___flymake.py
spacy_api/__main__.py
spacy_api/api.py
spacy_api/client.py
spacy_api/client_flymake.py
spacy_api/cors.py
spacy_api/old_flask.py
spacy_api/server.py
spacy_api/tree_view.py
spacy_api/view_tree.py
spacy_api-0.4.50.dist-info/DESCRIPTION.rst
spacy_api-0.4.50.dist-info/METADATA
spacy_api-0.4.50.dist-info/RECORD
spacy_api-0.4.50.dist-info/WHEEL
spacy_api-0.4.50.dist-info/entry_points.txt
spacy_api-0.4.50.dist-info/metadata.json
spacy_api-0.4.50.dist-info/top_level.txt
